kkpyai/kktorch.py
kkpyai-0.19.0.dist-info/LICENSE
kkpyai-0.19.0.dist-info/METADATA
kkpyai-0.19.0.dist-info/WHEEL
kkpyai-0.19.0.dist-info/RECORD
